flyweb/__init__.py
flyweb/_app.py
flyweb/_flyweb.py
flyweb/_server.py
flyweb/_server_stub.py
flyweb/components/__init__.py
flyweb/components/_components.py
flyweb/examples/counter/__main__.py
flyweb/examples/misc/__main__.py
flyweb/examples/stopwatch/__main__.py
flyweb/examples/todo/__main__.py
flyweb/static/index.html
flyweb/static/maquette.umd.js
flyweb/static/script.js
flyweb/static/socket.io.min.js
flyweb_framework-0.4.1.dist-info/METADATA
flyweb_framework-0.4.1.dist-info/WHEEL
flyweb_framework-0.4.1.dist-info/licenses/LICENSE
flyweb_framework-0.4.1.dist-info/RECORD
