Metadata-Version: 2.3
Name: flyweb-framework
Version: 0.4.1
Summary: Immediate-mode web framework
Project-URL: Homepage, https://github.com/girtsf/flyweb
Author-email: Girts Folkmanis <opensource@girts.me>
License-Expression: MIT
License-File: LICENSE
Requires-Python: >=3.10
Requires-Dist: anyio>=3.6
Requires-Dist: python-socketio>=5.7.2
Requires-Dist: typing-extensions>=4.5.0
Provides-Extra: examples
Requires-Dist: hypercorn>=0.14.3; extra == 'examples'
Provides-Extra: server
Requires-Dist: hypercorn>=0.14.3; extra == 'server'
